pytimeparse/VERSION
pytimeparse/__init__.py
pytimeparse/timeparse.py
pytimeparse/tests/__init__.py
pytimeparse/tests/testtimeparse.py
timeparse_plus-1.2.0.dist-info/LICENSE.rst
timeparse_plus-1.2.0.dist-info/METADATA
timeparse_plus-1.2.0.dist-info/WHEEL
timeparse_plus-1.2.0.dist-info/top_level.txt
timeparse_plus-1.2.0.dist-info/RECORD
