Metadata-Version: 2.1
Name: timeparse-plus
Version: 1.2.0
Summary: Time expression parser
Home-page: https://github.com/godwhoa/pytimeparse
Author: Will Roberts
Author-email: wildwilhelm@gmail.com
Maintainer: Joseph Daniel
Maintainer-email: gjdaniel1999@gmail.com
License: License :: OSI Approved :: MIT License
Keywords: time parsing parser
Platform: UNKNOWN
Classifier: Development Status :: 4 - Beta
Classifier: Intended Audience :: Developers
Classifier: Topic :: Text Processing
Classifier: Natural Language :: English
Classifier: License :: OSI Approved :: MIT License
Classifier: Programming Language :: Python :: 2
Classifier: Programming Language :: Python :: 2.7
Classifier: Programming Language :: Python :: 3
Classifier: Programming Language :: Python :: 3.2
Classifier: Programming Language :: Python :: 3.3
Classifier: Programming Language :: Python :: 3.4
Classifier: Programming Language :: Python :: 3.5
Classifier: Programming Language :: Python :: 3.6
Classifier: Programming Language :: Python :: 3.7
